{
  "name": "蓝宝石龙舌兰",
  "icon": "delta_delight:blue_sapphire_tequila",
  "category": "delta_delight:delta_food",
  "sortnum": 20,
  "secret": false,
  "pages": [
    {
      "type": "patchouli:spotlight",
      "item": "delta_delight:blue_sapphire_tequila",
      "title": "蓝宝石龙舌兰",
      "text": "$(o)「蓝宝石」——三角洲部队最负盛名的龙舌兰特调。晶莹剔透的蓝色酒液散发着幸运的光芒，一杯下肚，命运女神似乎都会对你微笑。$(br2)$(bold)品质$()：$(e)罕见$(/e)　$(bold)类型$()：饮品$(br)$(bold)容器$()：玻璃瓶　$(bold)可放置$()：是"
    },
    {
      "type": "patchouli:text",
      "title": "食用效果",
      "text": "$(li)幸运 $(6)II 2 分 40 秒$(/6)$(br2)饮用后返还空玻璃瓶。$(br)不提供饱食度，但足足 2 分 40 秒的幸运 II 效果——挖矿、钓鱼、刷战利品时的最佳伴侣。"
    },
    {
      "type": "patchouli:text",
      "title": "烹饪配方",
      "text": "$(bold)农夫乐事烹饪锅$()：$(li)甜浆果 ×3 或 红葡萄 ×3$(li)兰花 ×1$(li)海泡菜 ×1$(li)容器：玻璃瓶$(br2)$(bold)Vinery 发酵$()（可选路线）：$(li)红葡萄汁 35mB + 兰花 + 海泡菜"
    }
  ]
}
